<?xml version="1.0" encoding="utf-8"?>
<key id="ff442dbd-d35f-4c73-89cc-744adbf220c7" version="1">
  <creationDate>2021-09-15T07:29:54.590179Z</creationDate>
  <activationDate>2021-09-17T06:38:35.6985849Z</activationDate>
  <expirationDate>2022-03-14T07:29:54.474972Z</expirationDate>
  <descriptor deserializerType="Microsoft.AspNetCore.DataProtection.AuthenticatedEncryption.ConfigurationModel.AuthenticatedEncryptorDescriptorDeserializer, Microsoft.AspNetCore.DataProtection, Version=5.0.0.0, Culture=neutral, PublicKeyToken=adb9793829ddae60">
    <descriptor>
      <encryption algorithm="AES_256_CBC" />
      <validation algorithm="HMACSHA256" />
      <masterKey p4:requiresEncryption="true" xmlns:p4="http://schemas.asp.net/2015/03/dataProtection">
        <!-- Warning: the key below is in an unencrypted form. -->
        <value>dc6RfjQJ64+n0n2og9+P4NNDuou/nqv/ef3xFctPcwip2QKl+2af6UIpVYfU5wHQutyJMTeId8zh1O62rLRlzQ==</value>
      </masterKey>
    </descriptor>
  </descriptor>
</key>